{
  "nep-acc": "Accounting and Auditing",
  "nep-afr": "Africa",
  "nep-age": "Economics of Ageing",
  "nep-agr": "Agricultural Economics",
  "nep-ara": "MENA - Middle East and North Africa",
  "nep-ban": "Banking",
  "nep-bec": "Business Economics",
  "nep-big": "Big Data",
  "nep-cba": "Central Banking",
  "nep-cbe": "Cognitive and Behavioural Economics",
  "nep-cdm": "Collective Decision-Making",
  "nep-cfn": "Corporate Finance",
  "nep-cis": "Confederation of Independent States",
  "nep-cmp": "Computational Economics",
  "nep-cna": "China",
  "nep-com": "Industrial Competition",
  "nep-cse": "Economics of Strategic Management",
  "nep-cta": "Contract Theory and Applications",
  "nep-cul": "Cultural Economics",
  "nep-cwa": "Central and Western Asia",
  "nep-dcm": "Discrete Choice Models",
  "nep-dem": "Demographic Economics",
  "nep-des": "Economic Design",
  "nep-dev": "Development",
  "nep-dge": "Dynamic General Equilibrium",
  "nep-ecm": "Econometrics",
  "nep-edu": "Education",
  "nep-eec": "European Economics",
  "nep-eff": "Efficiency and Productivity",
  "nep-ene": "Energy Economics",
  "nep-ent": "Entrepreneurship",
  "nep-env": "Environmental Economics",
  "nep-ets": "Econometric Time Series",
  "nep-eur": "Microeconomic European Issues",
  "nep-evo": "Evolutionary Economics",
  "nep-exp": "Experimental Economics",
  "nep-fdg": "Financial Development and Growth",
  "nep-fle": "Financial Literacy and Education",
  "nep-fmk": "Financial Markets",
  "nep-for": "Forecasting",
  "nep-gen": "Gender",
  "nep-geo": "Economic Geography",
  "nep-ger": "German Papers",
  "nep-gro": "Economic Growth",
  "nep-gth": "Game Theory",
  "nep-hap": "Economics of Happiness",
  "nep-hea": "Health Economics",
  "nep-his": "Business, Economic and Financial History",
  "nep-hme": "Heterodox Microeconomics",
  "nep-hpe": "History and Philosophy of Economics",
  "nep-hrm": "Human Capital and Human Resource Management",
  "nep-ict": "Information and Communication Technologies",
  "nep-ifn": "International Finance",
  "nep-ind": "Industrial Organization",
  "nep-ino": "Innovation",
  "nep-int": "International Trade",
  "nep-ipr": "Intellectual Property Rights",
  "nep-isf": "Islamic Finance",
  "nep-iue": "Informal and Underground Economics",
  "nep-knm": "Knowledge Management and Knowledge Economy",
  "nep-lab": "Labour Economics",
  "nep-lam": "Central and South America",
  "nep-law": "Law and Economics",
  "nep-lma": "Labor Markets - Supply, Demand, and Wages",
  "nep-ltv": "Unemployment, Inequality and Poverty",
  "nep-mfd": "Microfinance",
  "nep-mic": "Microeconomics",
  "nep-mig": "Economics of Human Migration",
  "nep-mkt": "Marketing",
  "nep-mon": "Monetary Economics",
  "nep-mst": "Market Microstructure",
  "nep-net": "Network Economics",
  "nep-neu": "Neuroeconomics",
  "nep-opm": "Open Economy Macroeconomics",
  "nep-ore": "Operations Research",
  "nep-pay": "Payment Systems and Financial Technology",
  "nep-pbe": "Public Economics",
  "nep-pke": "Post Keynesian Economics",
  "nep-pol": "Positive Political Economics",
  "nep-ppm": "Project, Program and Portfolio Management",
  "nep-pub": "Public Finance",
  "nep-reg": "Regulation",
  "nep-res": "Resource Economics",
  "nep-rmg": "Risk Management",
  "nep-sbm": "Small Business Management",
  "nep-sea": "South East Asia",
  "nep-soc": "Social Norms and Social Capital",
  "nep-sog": "Sociology of Economics",
  "nep-spo": "Sports and Economics",
  "nep-tid": "Technology and Industrial Dynamics",
  "nep-tra": "Transition Economics",
  "nep-tre": "Transport Economics",
  "nep-tur": "Tourism Economics",
  "nep-upt": "Utility Models and Prospect Theory",
  "nep-ure": "Urban and Real Estate Economics"
}